bio_media/demo.txt
bio_polls/__init__.py
bio_polls/admin.py
bio_polls/api_urls.py
bio_polls/apps.py
bio_polls/models.py
bio_polls/serializers.py
bio_polls/tests.py
bio_polls/urls.py
bio_polls/views.py
bio_polls/fixtures/demo_data.json
bio_polls/migrations/0001_initial.py
bio_polls/migrations/__init__.py
bio_polls/static/favicon.ico
bio_polls/static/polls/style.css
bio_polls/static/polls/images/background.jpg
bio_polls/templates/polls/detail.html
bio_polls/templates/polls/header.html
bio_polls/templates/polls/index.html
bio_polls/templates/polls/results.html
bio_primer/__init__.py
bio_primer/admin.py
bio_primer/apps.py
bio_primer/models.py
bio_primer/primer.py
bio_primer/tests.py
bio_primer/urls.py
bio_primer/views.py
bio_primer/migrations/0001_initial.py
bio_primer/migrations/__init__.py
bio_primer/static/primer/index.js
bio_primer/static/primer/style.css
bio_primer/templates/primer/index.html
bio_showcase/__init__.py
bio_showcase/__main__.py
bio_showcase/asgi.py
bio_showcase/main.py
bio_showcase/nginx.conf
bio_showcase/pm.py
bio_showcase/settings.py
bio_showcase/urls.py
bio_showcase/wsgi.py
bio_showcase/templates/admin/base_site.html
bio_showcase-2025.5.20.2.dist-info/METADATA
bio_showcase-2025.5.20.2.dist-info/WHEEL
bio_showcase-2025.5.20.2.dist-info/entry_points.txt
bio_showcase-2025.5.20.2.dist-info/licenses/LICENSE
bio_showcase-2025.5.20.2.dist-info/RECORD
