Metadata-Version: 2.4
Name: bio-showcase
Version: 2025.5.20.2
Summary: Soda's Bioinformatics showcase
Project-URL: Repository, https://github.com/soda92/bio-showcase
License-File: LICENSE
Requires-Python: >=3.11
Requires-Dist: django-cors-headers>=4.7.0
Requires-Dist: django-debug-toolbar>=5.2.0
Requires-Dist: django>=5.2
Requires-Dist: djangorestframework>=3.16.0
Requires-Dist: primer3-py>=2.1.0
Requires-Dist: soda-nginx>=2025.5.13.5; sys_platform == 'win32'
Requires-Dist: soda-update-version>=2025.5.17.4
Requires-Dist: sodatools>=2025.2.16.0
Requires-Dist: uvicorn>=0.34.1
